Workbook

Sheet Supuestos
A1: Urban Eats – Supuestos del presupuesto
A2: Celdas en azul = entradas editables (amarillo = supuesto clave). Negro = fórmula. Verde = vínculo a otra hoja. Valores en pesos colombianos (COP).
A4: Concepto | B4: Valor | C4: Unidad | D4: Fuente / nota
A5: Salario mínimo mensual legal vigente 2026 (SMMLV) | B5: 1750905 | C5: COP/mes | D5: Decreto de salario mínimo 2026 (dato aportado por el equipo).
A6: Auxilio de transporte 2026 | B6: 249095 | C6: COP/mes | D6: Decreto de auxilio de transporte 2026 (dato aportado por el equipo). Aplica si el salario ≤ 2 SMMLV.
A7: Salario base desarrollador junior | B7: 2812680 | C7: COP/mes | D7: Indeed Colombia, 'Junior developer salaries', actualizado 14-sep-2026 (promedio nacional; Bogotá ≈ $2.827.195). https://co.indeed.com/career/junior-developer/salaries
A8: Jornada máxima semanal | B8: 42 | C8: h/semana | D8: Ley 2101 de 2021: reducción gradual; 42 h/semana desde el 15-jul-2026.
A9: Semanas promedio por mes | B9: =52/12 -> 4.3333333 | C9: semanas | D9: 52 semanas / 12 meses.
A10: Horas laborables por mes | B10: =B8*B9 -> 182 | C10: h/mes | D10: Jornada semanal × semanas por mes.
A12: Factor prestacional (a cargo del empleador)
A13: Prima de servicios | B13: 0.0833 | C13: % salario | D13: Código Sustantivo del Trabajo (CST) art. 306: 1 mes por año.
A14: Cesantías | B14: 0.0833 | C14: % salario | D14: CST art. 249: 1 mes por año.
A15: Intereses sobre cesantías | B15: 0.01 | C15: % salario | D15: Ley 52 de 1975: 12 % anual sobre cesantías.
A16: Vacaciones | B16: 0.0417 | C16: % salario | D16: CST art. 186: 15 días hábiles por año.
A17: Pensión (aporte empleador) | B17: 0.12 | C17: % salario | D17: Ley 100 de 1993: 12 % a cargo del empleador.
A18: Salud (aporte empleador) | B18: 0 | C18: % salario | D18: Exonerado: E.T. art. 114-1 para salarios < 10 SMMLV (8,5 % si no aplica).
A19: ARL riesgo I | B19: 0.00522 | C19: % salario | D19: Decreto 1772 de 1994: riesgo I = 0,522 %.
A20: Caja de compensación familiar | B20: 0.04 | C20: % salario | D20: Ley 21 de 1982: 4 %.
A21: ICBF y SENA (parafiscales) | B21: 0 | C21: % salario | D21: Exonerados por E.T. art. 114-1 (5 % si no aplica).
A22: Factor prestacional total | B22: =SUM(B13:B21) -> 0.38352 | C22: % salario | D22: Suma de los componentes anteriores.
A23: Costo mensual empleador por desarrollador | B23: =$B$7*(1+B22)+IF($B$7<=2*$B$5,$B$6,0) -> 4140494 | C23: COP/mes | D23: Salario × (1 + factor prestacional) + auxilio de transporte si salario ≤ 2 SMMLV.
A24: Tarifa por hora de desarrollador | B24: =B23/$B$10 -> 22749.967 | C24: COP/h | D24: Costo mensual empleador / horas laborables por mes.
A26: Dedicación y parámetros del proyecto
A27: Dedicación por integrante – fases 1 a 5 | B27: 10 | C27: h/semana | D27: Supuesto del equipo: trabajo académico a tiempo parcial (aprendices en formación + contrato de aprendizaje).
A28: Dedicación por integrante – fase 6 | B28: 20 | C28: h/semana | D28: Supuesto del equipo: sprints intensivos de 1 semana para cerrar el producto.
A29: Dedicación en periodos sin sprint formal | B29: 3 | C29: h/semana | D29: Supuesto: receso / planeación (pocos o ningún commit en el repositorio).
A30: TRM (dólar) | B30: 3170.46 | C30: COP/US$ | D30: TRM del 16-oct-2026, Superintendencia Financiera (reportada por Portafolio). https://www.portafolio.co/economia/finanzas/precio-del-dolar-hoy-en-colombia-asi-cotiza-la-divisa-este-16-de-octubre-tras-perder-casi-504569
A31: IVA general | B31: 0.19 | C31: % | D31: Estatuto Tributario art. 468.
A32: Vida útil de equipos de cómputo | B32: 5 | C32: años | D32: Decreto 1625 de 2016 / E.T. art. 137: equipos de cómputo, 5 años (tasa 20 % anual), línea recta.
A33: Contingencia | B33: 0.1 | C33: % subtotal | D33: Reserva para riesgos (estimación del equipo).
A34: MercadoPago – comisión porcentual | B34: 0.0329 | C34: % venta | D34: Dato del equipo: 3,29 % + COP 800 + IVA. La página oficial de Link de pago (oct-2026) muestra 3,29 % + IVA con liberación inmediata y sin cargo fijo: confirmar en la cuenta. https://www.mercadopago.com.co/herramientas-para-vender/link-de-pago
A35: MercadoPago – cargo fijo por transacción | B35: 800 | C35: COP | D35: Ver nota anterior (por confirmar).
A36: Ticket promedio de un pedido (piloto) | B36: 28000 | C36: COP | D36: Supuesto del equipo para estimar comisiones en un piloto real (no aplica en modo prueba).
A37: Costo de pasarela por pedido (con IVA) | B37: =(B36*B34+B35)*(1+$B$31) -> 2048.228 | C37: COP/pedido | D37: (Ticket × % + cargo fijo) × (1 + IVA).
A38: Pedidos reales durante el proyecto | B38: 0 | C38: pedidos | D38: 0: la pasarela se usa en modo prueba (sandbox), sin costo. Cambiar si se hace un piloto con pagos reales.

Sheet Resumen
A1: Resumen del presupuesto por sprint
A2: Hardware = depreciación semanal × semanas. Software se reparte por semanas en todo el proyecto. Contingencia = % de Supuestos sobre el subtotal.
A4: Sprint | B4: Fase | C4: Nombre | D4: Semanas | E4: Talento humano | F4: Hardware | G4: Software y licencias | H4: Servicios | I4: Subtotal | J4: Contingencia | K4: Total sprint | L4: % del total
A5: =Cronograma!A5 -> S1 | B5: =Cronograma!B5 -> Fases 1–5 | C5: =Cronograma!C5 -> Arranque y modelo de datos | D5: =Cronograma!F5 -> 2.7142857 | E5: ='Talento humano'!H5 -> 2469996.4 | F5: =Hardware!$E$10*D5 -> 91847.253 | G5: ='Software y licencias'!$G$15*D5/Cronograma!$F$21 -> 33369.662 | H5: =SUMIF(Servicios!$I$5:$I$11,"Proyecto",Servicios!$H$5:$H$11)*D5/Cronograma!$F$21+IF(B5="Fase 6",SUMIF(Servicios!$I$5:$I$11,"Fase 6",Servicios!$H$5:$H$11)*D5/Cronograma!$F$23,0) -> 33824.176 | I5: =SUM(E5:H5) -> 2629037.5 | J5: =I5*Supuestos!$B$33 -> 262903.75 | K5: =I5+J5 -> 2891941.3 | L5: =IF($K$21=0,0,K5/$K$21) -> 0.08227325
A6: =Cronograma!A6 -> S2 | B6: =Cronograma!B6 -> Fases 1–5 | C6: =Cronograma!C6 -> Base de datos avanzada y frontend base | D6: =Cronograma!F6 -> 2.2857143 | E6: ='Talento humano'!H6 -> 2079997 | F6: =Hardware!$E$10*D6 -> 77345.055 | G6: ='Software y licencias'!$G$15*D6/Cronograma!$F$21 -> 28100.768 | H6: =SUMIF(Servicios!$I$5:$I$11,"Proyecto",Servicios!$H$5:$H$11)*D6/Cronograma!$F$21+IF(B6="Fase 6",SUMIF(Servicios!$I$5:$I$11,"Fase 6",Servicios!$H$5:$H$11)*D6/Cronograma!$F$23,0) -> 28483.516 | I6: =SUM(E6:H6) -> 2213926.3 | J6: =I6*Supuestos!$B$33 -> 221392.63 | K6: =I6+J6 -> 2435319 | L6: =IF($K$21=0,0,K6/$K$21) -> 0.069282737
A7: =Cronograma!A7 -> S3 | B7: =Cronograma!B7 -> Fases 1–5 | C7: =Cronograma!C7 -> Diagramas, pagos (front) y documento DEA | D7: =Cronograma!F7 -> 4.2857143 | E7: ='Talento humano'!H7 -> 3899994.4 | F7: =Hardware!$E$10*D7 -> 145021.98 | G7: ='Software y licencias'!$G$15*D7/Cronograma!$F$21 -> 52688.94 | H7: =SUMIF(Servicios!$I$5:$I$11,"Proyecto",Servicios!$H$5:$H$11)*D7/Cronograma!$F$21+IF(B7="Fase 6",SUMIF(Servicios!$I$5:$I$11,"Fase 6",Servicios!$H$5:$H$11)*D7/Cronograma!$F$23,0) -> 53406.593 | I7: =SUM(E7:H7) -> 4151111.9 | J7: =I7*Supuestos!$B$33 -> 415111.19 | K7: =I7+J7 -> 4566223.1 | L7: =IF($K$21=0,0,K7/$K$21) -> 0.12990513
A8: =Cronograma!A8 -> S4 | B8: =Cronograma!B8 -> Fases 1–5 | C8: =Cronograma!C8 -> Normalización de la base de datos | D8: =Cronograma!F8 -> 4.4285714 | E8: ='Talento humano'!H8 -> 4029994.2 | F8: =Hardware!$E$10*D8 -> 149856.04 | G8: ='Software y licencias'!$G$15*D8/Cronograma!$F$21 -> 54445.238 | H8: =SUMIF(Servicios!$I$5:$I$11,"Proyecto",Servicios!$H$5:$H$11)*D8/Cronograma!$F$21+IF(B8="Fase 6",SUMIF(Servicios!$I$5:$I$11,"Fase 6",Servicios!$H$5:$H$11)*D8/Cronograma!$F$23,0) -> 55186.813 | I8: =SUM(E8:H8) -> 4289482.3 | J8: =I8*Supuestos!$B$33 -> 428948.23 | K8: =I8+J8 -> 4718430.5 | L8: =IF($K$21=0,0,K8/$K$21) -> 0.1342353
A9: =Cronograma!A9 -> S5 | B9: =Cronograma!B9 -> Fases 1–5 | C9: =Cronograma!C9 -> Migración a Laravel: autenticación | D9: =Cronograma!F9 -> 2.2857143 | E9: ='Talento humano'!H9 -> 2079997 | F9: =Hardware!$E$10*D9 -> 77345.055 | G9: ='Software y licencias'!$G$15*D9/Cronograma!$F$21 -> 28100.768 | H9: =SUMIF(Servicios!$I$5:$I$11,"Proyecto",Servicios!$H$5:$H$11)*D9/Cronograma!$F$21+IF(B9="Fase 6",SUMIF(Servicios!$I$5:$I$11,"Fase 6",Servicios!$H$5:$H$11)*D9/Cronograma!$F$23,0) -> 28483.516 | I9: =SUM(E9:H9) -> 2213926.3 | J9: =I9*Supuestos!$B$33 -> 221392.63 | K9: =I9+J9 -> 2435319 | L9: =IF($K$21=0,0,K9/$K$21) -> 0.069282737
A10: =Cronograma!A10 -> S6 | B10: =Cronograma!B10 -> Fases 1–5 | C10: =Cronograma!C10 -> Pasarela MercadoPago y chatbot | D10: =Cronograma!F10 -> 4 | E10: ='Talento humano'!H10 -> 3639994.8 | F10: =Hardware!$E$10*D10 -> 135353.85 | G10: ='Software y licencias'!$G$15*D10/Cronograma!$F$21 -> 49176.344 | H10: =SUMIF(Servicios!$I$5:$I$11,"Proyecto",Servicios!$H$5:$H$11)*D10/Cronograma!$F$21+IF(B10="Fase 6",SUMIF(Servicios!$I$5:$I$11,"Fase 6",Servicios!$H$5:$H$11)*D10/Cronograma!$F$23,0) -> 49846.154 | I10: =SUM(E10:H10) -> 3874371.1 | J10: =I10*Supuestos!$B$33 -> 387437.11 | K10: =I10+J10 -> 4261808.2 | L10: =IF($K$21=0,0,K10/$K$21) -> 0.12124479
A11: =Cronograma!A11 -> S7 | B11: =Cronograma!B11 -> Fases 1–5 | C11: =Cronograma!C11 -> Receso y transición (sin sprint formal) | D11: =Cronograma!F11 -> 4.5714286 | E11: ='Talento humano'!H11 -> 1247998.2 | F11: =Hardware!$E$10*D11 -> 154690.11 | G11: ='Software y licencias'!$G$15*D11/Cronograma!$F$21 -> 56201.536 | H11: =SUMIF(Servicios!$I$5:$I$11,"Proyecto",Servicios!$H$5:$H$11)*D11/Cronograma!$F$21+IF(B11="Fase 6",SUMIF(Servicios!$I$5:$I$11,"Fase 6",Servicios!$H$5:$H$11)*D11/Cronograma!$F$23,0) -> 56967.033 | I11: =SUM(E11:H11) -> 1515856.9 | J11: =I11*Supuestos!$B$33 -> 151585.69 | K11: =I11+J11 -> 1667442.6 | L11: =IF($K$21=0,0,K11/$K$21) -> 0.047437311
A12: =Cronograma!A12 -> S8 | B12: =Cronograma!B12 -> Fases 1–5 | C12: =Cronograma!C12 -> Migración a Spring Boot: entidades y DAO | D12: =Cronograma!F12 -> 2.2857143 | E12: ='Talento humano'!H12 -> 2079997 | F12: =Hardware!$E$10*D12 -> 77345.055 | G12: ='Software y licencias'!$G$15*D12/Cronograma!$F$21 -> 28100.768 | H12: =SUMIF(Servicios!$I$5:$I$11,"Proyecto",Servicios!$H$5:$H$11)*D12/Cronograma!$F$21+IF(B12="Fase 6",SUMIF(Servicios!$I$5:$I$11,"Fase 6",Servicios!$H$5:$H$11)*D12/Cronograma!$F$23,0) -> 28483.516 | I12: =SUM(E12:H12) -> 2213926.3 | J12: =I12*Supuestos!$B$33 -> 221392.63 | K12: =I12+J12 -> 2435319 | L12: =IF($K$21=0,0,K12/$K$21) -> 0.069282737
A13: =Cronograma!A13 -> S9 | B13: =Cronograma!B13 -> Fases 1–5 | C13: =Cronograma!C13 -> Servicios, controladores y reportes | D13: =Cronograma!F13 -> 2 | E13: ='Talento humano'!H13 -> 1819997.4 | F13: =Hardware!$E$10*D13 -> 67676.923 | G13: ='Software y licencias'!$G$15*D13/Cronograma!$F$21 -> 24588.172 | H13: =SUMIF(Servicios!$I$5:$I$11,"Proyecto",Servicios!$H$5:$H$11)*D13/Cronograma!$F$21+IF(B13="Fase 6",SUMIF(Servicios!$I$5:$I$11,"Fase 6",Servicios!$H$5:$H$11)*D13/Cronograma!$F$23,0) -> 24923.077 | I13: =SUM(E13:H13) -> 1937185.5 | J13: =I13*Supuestos!$B$33 -> 193718.55 | K13: =I13+J13 -> 2130904.1 | L13: =IF($K$21=0,0,K13/$K$21) -> 0.060622395
A14: =Cronograma!A14 -> S10 | B14: =Cronograma!B14 -> Fases 1–5 | C14: =Cronograma!C14 -> Planeación de fase 6 (sin commits) | D14: =Cronograma!F14 -> 4.8571429 | E14: ='Talento humano'!H14 -> 662999.04 | F14: =Hardware!$E$10*D14 -> 164358.24 | G14: ='Software y licencias'!$G$15*D14/Cronograma!$F$21 -> 59714.132 | H14: =SUMIF(Servicios!$I$5:$I$11,"Proyecto",Servicios!$H$5:$H$11)*D14/Cronograma!$F$21+IF(B14="Fase 6",SUMIF(Servicios!$I$5:$I$11,"Fase 6",Servicios!$H$5:$H$11)*D14/Cronograma!$F$23,0) -> 60527.473 | I14: =SUM(E14:H14) -> 947598.89 | J14: =I14*Supuestos!$B$33 -> 94759.889 | K14: =I14+J14 -> 1042358.8 | L14: =IF($K$21=0,0,K14/$K$21) -> 0.029654214
A15: =Cronograma!A15 -> F6-1 | B15: =Cronograma!B15 -> Fase 6 | C15: =Cronograma!C15 -> Estabilizar | D15: =Cronograma!F15 -> 1 | E15: ='Talento humano'!H15 -> 909998.69 | F15: =Hardware!$E$10*D15 -> 33838.462 | G15: ='Software y licencias'!$G$15*D15/Cronograma!$F$21 -> 12294.086 | H15: =SUMIF(Servicios!$I$5:$I$11,"Proyecto",Servicios!$H$5:$H$11)*D15/Cronograma!$F$21+IF(B15="Fase 6",SUMIF(Servicios!$I$5:$I$11,"Fase 6",Servicios!$H$5:$H$11)*D15/Cronograma!$F$23,0) -> 38623.118 | I15: =SUM(E15:H15) -> 994754.35 | J15: =I15*Supuestos!$B$33 -> 99475.435 | K15: =I15+J15 -> 1094229.8 | L15: =IF($K$21=0,0,K15/$K$21) -> 0.031129899
A16: =Cronograma!A16 -> F6-2 | B16: =Cronograma!B16 -> Fase 6 | C16: =Cronograma!C16 -> Servicio Python | D16: =Cronograma!F16 -> 1 | E16: ='Talento humano'!H16 -> 909998.69 | F16: =Hardware!$E$10*D16 -> 33838.462 | G16: ='Software y licencias'!$G$15*D16/Cronograma!$F$21 -> 12294.086 | H16: =SUMIF(Servicios!$I$5:$I$11,"Proyecto",Servicios!$H$5:$H$11)*D16/Cronograma!$F$21+IF(B16="Fase 6",SUMIF(Servicios!$I$5:$I$11,"Fase 6",Servicios!$H$5:$H$11)*D16/Cronograma!$F$23,0) -> 38623.118 | I16: =SUM(E16:H16) -> 994754.35 | J16: =I16*Supuestos!$B$33 -> 99475.435 | K16: =I16+J16 -> 1094229.8 | L16: =IF($K$21=0,0,K16/$K$21) -> 0.031129899
... A20: =Cronograma!A20 -> F6-6 | B20: =Cronograma!B20 -> Fase 6 | C20: =Cronograma!C20 -> Documentar y ensayar | D20: =Cronograma!F20 -> 1 | E20: ='Talento humano'!H20 -> 909998.69 | F20: =Hardware!$E$10*D20 -> 33838.462 | G20: ='Software y licencias'!$G$15*D20/Cronograma!$F$21 -> 12294.086 | H20: =SUMIF(Servicios!$I$5:$I$11,"Proyecto",Servicios!$H$5:$H$11)*D20/Cronograma!$F$21+IF(B20="Fase 6",SUMIF(Servicios!$I$5:$I$11,"Fase 6",Servicios!$H$5:$H$11)*D20/Cronograma!$F$23,0) -> 38623.118 | I20: =SUM(E20:H20) -> 994754.35 | J20: =I20*Supuestos!$B$33 -> 99475.435 | K20: =I20+J20 -> 1094229.8 | L20: =IF($K$21=0,0,K20/$K$21) -> 0.031129899
C21: TOTAL PROYECTO | D21: =SUM(D5:D20) -> 39.714286 | E21: =SUM(E5:E20) -> 29470958 | F21: =SUM(F5:F20) -> 1343870.3 | G21: =SUM(G5:G20) -> 488250.84 | H21: =SUM(H5:H20) -> 651870.57 | I21: =SUM(I5:I20) -> 31954949 | J21: =SUM(J5:J20) -> 3195494.9 | K21: =SUM(K5:K20) -> 35150444 | L21: =SUM(L5:L20) -> 1
C23: Totales por fase
C24: Fases 1–5 | E24: =SUMIF($B$5:$B$20,"Fases 1–5",E$5:E$20) -> 24010965 | F24: =SUMIF($B$5:$B$20,"Fases 1–5",F$5:F$20) -> 1140839.6 | G24: =SUMIF($B$5:$B$20,"Fases 1–5",G$5:G$20) -> 414486.32 | H24: =SUMIF($B$5:$B$20,"Fases 1–5",H$5:H$20) -> 420131.87 | I24: =SUMIF($B$5:$B$20,"Fases 1–5",I$5:I$20) -> 25986423 | J24: =SUMIF($B$5:$B$20,"Fases 1–5",J$5:J$20) -> 2598642.3 | K24: =SUMIF($B$5:$B$20,"Fases 1–5",K$5:K$20) -> 28585065
C25: Fase 6 | E25: =SUMIF($B$5:$B$20,"Fase 6",E$5:E$20) -> 5459992.1 | F25: =SUMIF($B$5:$B$20,"Fase 6",F$5:F$20) -> 203030.77 | G25: =SUMIF($B$5:$B$20,"Fase 6",G$5:G$20) -> 73764.515 | H25: =SUMIF($B$5:$B$20,"Fase 6",H$5:H$20) -> 231738.71 | I25: =SUMIF($B$5:$B$20,"Fase 6",I$5:I$20) -> 5968526.1 | J25: =SUMIF($B$5:$B$20,"Fase 6",J$5:J$20) -> 596852.61 | K25: =SUMIF($B$5:$B$20,"Fase 6",K$5:K$20) -> 6565378.7
C27: Controles
C28: Talento humano = hoja Talento humano | E28: =IF(ABS(E21-'Talento humano'!H21)<1,"OK","REVISAR") -> OK
C29: Hardware resumen = hoja Hardware | E29: =IF(ABS(F21-Hardware!G8)<1,"OK","REVISAR") -> OK
C30: Servicios resumen = hoja Servicios | E30: =IF(ABS(H21-Servicios!H12)<1,"OK","REVISAR") -> OK
C31: Software resumen = hoja Software | E31: =IF(ABS(G21-'Software y licencias'!$G$15)<1,"OK","REVISAR") -> OK

Sheet Cronograma
A1: Cronograma por sprints
A2: Sprints 1–9 reconstruidos del historial de git del repositorio SDDev-01/Urban-Eats (293 commits, 25-feb a 14-sep-2026). Fase 6: 6 sprints de 1 semana.
A4: Sprint | B4: Fase | C4: Nombre | D4: Inicio | E4: Fin | F4: Semanas | G4: Integrantes | H4: h/semana por integrante | I4: Horas sprint | J4: Entregables (según commits)
A5: S1 | B5: Fases 1–5 | C5: Arranque y modelo de datos | D5: 46078 | E5: 46096 | F5: =(E5-D5+1)/7 -> 2.7142857 | G5: 4 | H5: =Supuestos!$B$27 -> 10 | I5: =F5*G5*H5 -> 108.57143 | J5: Repositorio, modelo relacional, scripts Schema.sql e Inserts.sql.
A6: S2 | B6: Fases 1–5 | C6: Base de datos avanzada y frontend base | D6: 46097 | E6: 46112 | F6: =(E6-D6+1)/7 -> 2.2857143 | G6: 4 | H6: =Supuestos!$B$27 -> 10 | I6: =F6*G6*H6 -> 91.428571 | J6: Triggers, funciones y procedimientos; frontend HTML/CSS; catálogo; rastreo con mapa; diagramas de despliegue y paquetes; páginas 404/500.
A7: S3 | B7: Fases 1–5 | C7: Diagramas, pagos (front) y documento DEA | D7: 46113 | E7: 46142 | F7: =(E7-D7+1)/7 -> 4.2857143 | G7: 4 | H7: =Supuestos!$B$27 -> 10 | I7: =F7*G7*H7 -> 171.42857 | J7: Vista de método de pago, diagramas de componentes y paquetes, DEA con objetivos SMART.
A8: S4 | B8: Fases 1–5 | C8: Normalización de la base de datos | D8: 46143 | E8: 46173 | F8: =(E8-D8+1)/7 -> 4.4285714 | G8: 4 | H8: =Supuestos!$B$27 -> 10 | I8: =F8*G8*H8 -> 177.14286 | J8: Modelo relacional normalizado, rol gerente, compatibilidad MySQL/MariaDB.
A9: S5 | B9: Fases 1–5 | C9: Migración a Laravel: autenticación | D9: 46174 | E9: 46189 | F9: =(E9-D9+1)/7 -> 2.2857143 | G9: 4 | H9: =Supuestos!$B$27 -> 10 | I9: =F9*G9*H9 -> 91.428571 | J9: Vistas Laravel, inicio de sesión, registro, logout, controladores de restaurante y rastreo.
A10: S6 | B10: Fases 1–5 | C10: Pasarela MercadoPago y chatbot | D10: 46190 | E10: 46217 | F10: =(E10-D10+1)/7 -> 4 | G10: 4 | H10: =Supuestos!$B$27 -> 10 | I10: =F10*G10*H10 -> 160 | J10: Integración MercadoPago, chatbot con API externa, imágenes de restaurantes.
A11: S7 | B11: Fases 1–5 | C11: Receso y transición (sin sprint formal) | D11: 46218 | E11: 46249 | F11: =(E11-D11+1)/7 -> 4.5714286 | G11: 4 | H11: =Supuestos!$B$29 -> 3 | I11: =F11*G11*H11 -> 54.857143 | J11: Conversión de vistas PHP a HTML (pocos commits).
A12: S8 | B12: Fases 1–5 | C12: Migración a Spring Boot: entidades y DAO | D12: 46250 | E12: 46265 | F12: =(E12-D12+1)/7 -> 2.2857143 | G12: 4 | H12: =Supuestos!$B$27 -> 10 | I12: =F12*G12*H12 -> 91.428571 | J12: Configuración Java 21 + Spring Boot, entidades JPA, repositorios y cardinalidades.
A13: S9 | B13: Fases 1–5 | C13: Servicios, controladores y reportes | D13: 46266 | E13: 46279 | F13: =(E13-D13+1)/7 -> 2 | G13: 4 | H13: =Supuestos!$B$27 -> 10 | I13: =F13*G13*H13 -> 80 | J13: Services e interfaces, controllers, login corregido, reporte de platos con filtros multicriterio.
A14: S10 | B14: Fases 1–5 | C14: Planeación de fase 6 (sin commits) | D14: 46280 | E14: 46313 | F14: =(E14-D14+1)/7 -> 4.8571429 | G14: 2 | H14: =Supuestos!$B$29 -> 3 | I14: =F14*G14*H14 -> 29.142857 | J14: Sin commits en el repositorio: cierre de fase 5, reorganización del equipo (pasa a 2 integrantes) y planeación.
A15: F6-1 | B15: Fase 6 | C15: Estabilizar | D15: 46314 | E15: =D15+6 -> 46320 | F15: =(E15-D15+1)/7 -> 1 | G15: 2 | H15: =Supuestos!$B$28 -> 20 | I15: =F15*G15*H15 -> 40 | J15: Flujo de pedidos con 3 roles y 6 estados corregido; errores de arranque resueltos.
A16: F6-2 | B16: Fase 6 | C16: Servicio Python | D16: =E15+1 -> 46321 | E16: =D16+6 -> 46327 | F16: =(E16-D16+1)/7 -> 1 | G16: 2 | H16: =Supuestos!$B$28 -> 20 | I16: =F16*G16*H16 -> 40 | J16: Microservicio FastAPI: CRUD de solicitudes de cocina, validaciones try/except, estructura de carpetas.
A17: F6-3 | B17: Fase 6 | C17: IA, mapa e integración | D17: =E16+1 -> 46328 | E17: =D17+6 -> 46334 | F17: =(E17-D17+1)/7 -> 1 | G17: 2 | H17: =Supuestos!$B$28 -> 20 | I17: =F17*G17*H17 -> 40 | J17: Chatbot con Ollama qwen3:4b, ruta OpenRouteService en mapa Leaflet, integración Spring ↔ Python.
A18: F6-4 | B18: Fase 6 | C18: Demostración y calidad | D18: =E17+1 -> 46335 | E18: =D18+6 -> 46341 | F18: =(E18-D18+1)/7 -> 1 | G18: 2 | H18: =Supuestos!$B$28 -> 20 | I18: =F18*G18*H18 -> 40 | J18: Modo demostración con cocina y datos de prueba; ejecución del plan de pruebas.
A19: F6-5 | B19: Fase 6 | C19: Extras | D19: =E18+1 -> 46342 | E19: =D19+6 -> 46348 | F19: =(E19-D19+1)/7 -> 1 | G19: 2 | H19: =Supuestos!$B$28 -> 20 | I19: =F19*G19*H19 -> 40 | J19: Reportes exportables CSV/XLSX/PDF, mejoras de interfaz, acciones de mejora de las pruebas.
A20: F6-6 | B20: Fase 6 | C20: Documentar y ensayar | D20: =E19+1 -> 46349 | E20: =D20+6 -> 46355 | F20: =(E20-D20+1)/7 -> 1 | G20: 2 | H20: =Supuestos!$B$28 -> 20 | I20: =F20*G20*H20 -> 40 | J20: Negociación tecnológica, presupuesto, diapositivas, encuesta y ensayo de la sustentación.
C21: TOTAL PROYECTO | D21: =MIN(D5:D20) -> 46078 | E21: =MAX(E5:E20) -> 46355 | F21: =SUM(F5:F20) -> 39.714286 | I21: =SUM(I5:I20) -> 1295.4286
C22: Meses del proyecto | F22: =F21/Supuestos!$B$9 -> 9.1648352
C23: Semanas de la fase 6 | F23: =SUMIF(B5:B20,"Fase 6",F5:F20) -> 6

Sheet Talento humano
A1: Talento humano por sprint
A2: Costo = integrantes × horas por integrante en el sprint × tarifa por hora (hoja Supuestos). Se valora a precio de mercado aunque el equipo sea de aprendices.
A4: Sprint | B4: Fase | C4: Nombre | D4: Integrantes | E4: h por integrante | F4: Horas totales | G4: Tarifa hora | H4: Costo talento humano
A5: =Cronograma!A5 -> S1 | B5: =Cronograma!B5 -> Fases 1–5 | C5: =Cronograma!C5 -> Arranque y modelo de datos | D5: =Cronograma!G5 -> 4 | E5: =Cronograma!F5*Cronograma!H5 -> 27.142857 | F5: =D5*E5 -> 108.57143 | G5: =Supuestos!$B$24 -> 22749.967 | H5: =F5*G5 -> 2469996.4
A6: =Cronograma!A6 -> S2 | B6: =Cronograma!B6 -> Fases 1–5 | C6: =Cronograma!C6 -> Base de datos avanzada y frontend base | D6: =Cronograma!G6 -> 4 | E6: =Cronograma!F6*Cronograma!H6 -> 22.857143 | F6: =D6*E6 -> 91.428571 | G6: =Supuestos!$B$24 -> 22749.967 | H6: =F6*G6 -> 2079997
A7: =Cronograma!A7 -> S3 | B7: =Cronograma!B7 -> Fases 1–5 | C7: =Cronograma!C7 -> Diagramas, pagos (front) y documento DEA | D7: =Cronograma!G7 -> 4 | E7: =Cronograma!F7*Cronograma!H7 -> 42.857143 | F7: =D7*E7 -> 171.42857 | G7: =Supuestos!$B$24 -> 22749.967 | H7: =F7*G7 -> 3899994.4
A8: =Cronograma!A8 -> S4 | B8: =Cronograma!B8 -> Fases 1–5 | C8: =Cronograma!C8 -> Normalización de la base de datos | D8: =Cronograma!G8 -> 4 | E8: =Cronograma!F8*Cronograma!H8 -> 44.285714 | F8: =D8*E8 -> 177.14286 | G8: =Supuestos!$B$24 -> 22749.967 | H8: =F8*G8 -> 4029994.2
A9: =Cronograma!A9 -> S5 | B9: =Cronograma!B9 -> Fases 1–5 | C9: =Cronograma!C9 -> Migración a Laravel: autenticación | D9: =Cronograma!G9 -> 4 | E9: =Cronograma!F9*Cronograma!H9 -> 22.857143 | F9: =D9*E9 -> 91.428571 | G9: =Supuestos!$B$24 -> 22749.967 | H9: =F9*G9 -> 2079997
A10: =Cronograma!A10 -> S6 | B10: =Cronograma!B10 -> Fases 1–5 | C10: =Cronograma!C10 -> Pasarela MercadoPago y chatbot | D10: =Cronograma!G10 -> 4 | E10: =Cronograma!F10*Cronograma!H10 -> 40 | F10: =D10*E10 -> 160 | G10: =Supuestos!$B$24 -> 22749.967 | H10: =F10*G10 -> 3639994.8
A11: =Cronograma!A11 -> S7 | B11: =Cronograma!B11 -> Fases 1–5 | C11: =Cronograma!C11 -> Receso y transición (sin sprint formal) | D11: =Cronograma!G11 -> 4 | E11: =Cronograma!F11*Cronograma!H11 -> 13.714286 | F11: =D11*E11 -> 54.857143 | G11: =Supuestos!$B$24 -> 22749.967 | H11: =F11*G11 -> 1247998.2
A12: =Cronograma!A12 -> S8 | B12: =Cronograma!B12 -> Fases 1–5 | C12: =Cronograma!C12 -> Migración a Spring Boot: entidades y DAO | D12: =Cronograma!G12 -> 4 | E12: =Cronograma!F12*Cronograma!H12 -> 22.857143 | F12: =D12*E12 -> 91.428571 | G12: =Supuestos!$B$24 -> 22749.967 | H12: =F12*G12 -> 2079997
A13: =Cronograma!A13 -> S9 | B13: =Cronograma!B13 -> Fases 1–5 | C13: =Cronograma!C13 -> Servicios, controladores y reportes | D13: =Cronograma!G13 -> 4 | E13: =Cronograma!F13*Cronograma!H13 -> 20 | F13: =D13*E13 -> 80 | G13: =Supuestos!$B$24 -> 22749.967 | H13: =F13*G13 -> 1819997.4
A14: =Cronograma!A14 -> S10 | B14: =Cronograma!B14 -> Fases 1–5 | C14: =Cronograma!C14 -> Planeación de fase 6 (sin commits) | D14: =Cronograma!G14 -> 2 | E14: =Cronograma!F14*Cronograma!H14 -> 14.571429 | F14: =D14*E14 -> 29.142857 | G14: =Supuestos!$B$24 -> 22749.967 | H14: =F14*G14 -> 662999.04
A15: =Cronograma!A15 -> F6-1 | B15: =Cronograma!B15 -> Fase 6 | C15: =Cronograma!C15 -> Estabilizar | D15: =Cronograma!G15 -> 2 | E15: =Cronograma!F15*Cronograma!H15 -> 20 | F15: =D15*E15 -> 40 | G15: =Supuestos!$B$24 -> 22749.967 | H15: =F15*G15 -> 909998.69
A16: =Cronograma!A16 -> F6-2 | B16: =Cronograma!B16 -> Fase 6 | C16: =Cronograma!C16 -> Servicio Python | D16: =Cronograma!G16 -> 2 | E16: =Cronograma!F16*Cronograma!H16 -> 20 | F16: =D16*E16 -> 40 | G16: =Supuestos!$B$24 -> 22749.967 | H16: =F16*G16 -> 909998.69
... A20: =Cronograma!A20 -> F6-6 | B20: =Cronograma!B20 -> Fase 6 | C20: =Cronograma!C20 -> Documentar y ensayar | D20: =Cronograma!G20 -> 2 | E20: =Cronograma!F20*Cronograma!H20 -> 20 | F20: =D20*E20 -> 40 | G20: =Supuestos!$B$24 -> 22749.967 | H20: =F20*G20 -> 909998.69
C21: TOTAL | F21: =SUM(F5:F20) -> 1295.4286 | H21: =SUM(H5:H20) -> 29470958

Sheet Hardware
A1: Hardware – depreciación prorrateada
A2: Depreciación en línea recta a 5 años (60 meses). Se carga al proyecto solo la depreciación de los meses de uso. Precios con IVA incluido.
A4: Equipo | B4: Cantidad | C4: Valor unitario | D4: Valor total | E4: Depreciación mensual | F4: Meses de uso | G4: Costo imputado | H4: Fuente / nota
A5: Portátil Intel Core i7, 16 GB RAM, SSD 512 GB | B5: 2 | C5: 4399000 | D5: =B5*C5 -> 8798000 | E5: =D5/(Supuestos!$B$32*12) -> 146633.33 | F5: =Cronograma!$F$22 -> 9.1648352 | G5: =E5*F5 -> 1343870.3 | H5: Precio de lista Acer Aspire Lite 16" (Core i7, 16 GB, 512 GB) en Alkomprar/Alkosto, 2026. https://www.alkomprar.com/computador-portatil-acer-aspire-lite-16-pulgadas-7167/p/4711474847195
A6: GPU dedicada 4 GB (opcional, acelera Ollama) | B6: 0 | C6: 1200000 | D6: =B6*C6 -> 0 | E6: =D6/(Supuestos!$B$32*12) -> 0 | F6: =Cronograma!$F$22 -> 9.1648352 | G6: =E6*F6 -> 0 | H6: Opcional: qwen3:4b corre en CPU con 16 GB RAM. Valor de referencia por confirmar; cantidad 0 = no se compra.
A7: Servidor de producción (mín. 2 vCPU, 8 GB RAM, 100 GB) | B7: 0 | C7: 0 | D7: =B7*C7 -> 0 | E7: =D7/(Supuestos!$B$32*12) -> 0 | F7: =Cronograma!$F$22 -> 9.1648352 | G7: =E7*F7 -> 0 | H7: No se compra: se arrienda como VPS (ver hoja Servicios).
A8: TOTAL | D8: =SUM(D5:D7) -> 8798000 | E8: =SUM(E5:E7) -> 146633.33 | G8: =SUM(G5:G7) -> 1343870.3
A10: Depreciación por semana (para el resumen por sprint) | E10: =E8/Supuestos!$B$9 -> 33838.462

Sheet Software y licencias
A1: Software y licencias
A2: Todo el stack es software libre o gratuito. La única licencia con costo es la tipografía Cocogoose Pro (hoy en versión trial).
A4: Software | B4: Uso en el proyecto | C4: Licencia | D4: Precio US$ | E4: Precio COP | F4: Cantidad | G4: Total COP | H4: Fuente / nota
A5: Java 21 (Eclipse Temurin) | B5: Backend principal | C5: GPLv2 + Classpath Exception | D5: 0 | E5: =D5*Supuestos!$B$30 -> 0 | F5: 1 | G5: =E5*F5 -> 0 | H5: https://adoptium.net
A6: Spring Boot 4.1 + Thymeleaf | B6: Framework web y vistas | C6: Apache 2.0 | D6: 0 | E6: =D6*Supuestos!$B$30 -> 0 | F6: 1 | G6: =E6*F6 -> 0 | H6: https://spring.io/projects/spring-boot
A7: Python 3.13 + FastAPI + SQLAlchemy | B7: Microservicio de verificación y reportes | C7: PSF / MIT / MIT | D7: 0 | E7: =D7*Supuestos!$B$30 -> 0 | F7: 1 | G7: =E7*F7 -> 0 | H7: https://fastapi.tiangolo.com
A8: MariaDB 10.4 / MySQL Community | B8: Base de datos | C8: GPLv2 | D8: 0 | E8: =D8*Supuestos!$B$30 -> 0 | F8: 1 | G8: =E8*F8 -> 0 | H8: https://mariadb.org
A9: Ollama + modelo qwen3:4b | B9: Asistente IA local | C9: MIT / Apache 2.0 | D9: 0 | E9: =D9*Supuestos!$B$30 -> 0 | F9: 1 | G9: =E9*F9 -> 0 | H9: https://ollama.com/library/qwen3
A10: Leaflet + OpenStreetMap | B10: Mapa y teselas | C10: BSD-2 / ODbL | D10: 0 | E10: =D10*Supuestos!$B$30 -> 0 | F10: 1 | G10: =E10*F10 -> 0 | H10: https://leafletjs.com · https://www.openstreetmap.org/copyright
A11: VS Code / IntelliJ IDEA Community | B11: Entorno de desarrollo | C11: MIT / Apache 2.0 | D11: 0 | E11: =D11*Supuestos!$B$30 -> 0 | F11: 1 | G11: =E11*F11 -> 0 | H11: Ediciones gratuitas.
A12: Git + GitHub Free | B12: Control de versiones y tablero | C12: GPLv2 / plan gratuito | D12: 0 | E12: =D12*Supuestos!$B$30 -> 0 | F12: 1 | G12: =E12*F12 -> 0 | H12: https://github.com/pricing
A13: Creato Display | B13: Tipografía de cuerpo | C13: Gratuita (verificar términos de uso comercial) | D13: 0 | E13: =D13*Supuestos!$B$30 -> 0 | F13: 1 | G13: =E13*F13 -> 0 | H13: Tipografía del manual de identidad.
A14: Cocogoose Pro – familia completa (licencia de escritorio) | B14: Tipografía de títulos | C14: Comercial – Zetafonts | D14: 154 | E14: =D14*Supuestos!$B$30 -> 488250.84 | F14: 1 | G14: =E14*F14 -> 488250.84 | H14: Referencia: YouWorkForThem, familia completa US$154. https://www.youworkforthem.com/font/T7362/cocogoose-pro · La web requiere licencia webfont aparte: confirmar con Zetafonts o reemplazar por una fuente libre (p. ej. Poppins, OFL) con costo 0.
A15: TOTAL | G15: =SUM(G5:G14) -> 488250.84

Sheet Servicios
A1: Servicios
A2: Ámbito 'Proyecto' se reparte entre todos los sprints por semanas; ámbito 'Fase 6' solo entre los sprints de la fase 6.
A4: Servicio | B4: Proveedor | C4: Unidad | D4: Precio US$ | E4: Precio COP | F4: Cantidad | G4: Periodos | H4: Total COP | I4: Ámbito | J4: Fuente / nota
A5: VPS producción (2 vCPU, 8 GB, 100 GB NVMe) | B5: Hostinger KVM 2 | C5: mes | D5: 16.99 | E5: =D5*Supuestos!$B$30 -> 53866.115 | F5: 1 | G5: 2 | H5: =E5*F5*G5 -> 107732.23 | I5: Fase 6 | J5: US$16,99/mes con compromiso de 12 meses (US$24,49 sin compromiso). VPSBenchmarks, oct-2026: https://www.vpsbenchmarks.com/hosters/hostinger/plans/kvm-2 · Se imputan 2 meses de despliegue para la demostración.
A6: Dominio urbaneats.com.co | B6: Spaceship (registrador) | C6: año | D6: 15.53 | E6: =D6*Supuestos!$B$30 -> 49237.244 | F6: 1 | G6: 1 | H6: =E6*F6*G6 -> 49237.244 | I6: Fase 6 | J6: US$15,53/año registro y renovación: https://www.spaceship.com/zh-HK/domains/cctld/com-co/ · OVHcloud lo ofrece en US$13,59 el primer año.
A7: OpenRouteService – Directions | B7: HeiGIT | C7: día | D7: 0 | E7: =D7*Supuestos!$B$30 -> 0 | F7: 1 | G7: 1 | H7: =E7*F7*G7 -> 0 | I7: Fase 6 | J7: Plan Standard gratuito: 2.000 rutas/día y 40/min con API key. https://openrouteservice.org/plans/
A8: Teselas de OpenStreetMap | B8: OSM Foundation | C8: mes | D8: 0 | E8: =D8*Supuestos!$B$30 -> 0 | F8: 1 | G8: 1 | H8: =E8*F8*G8 -> 0 | I8: Fase 6 | J8: Gratis con atribución y uso moderado (Tile Usage Policy). https://operations.osmfoundation.org/policies/tiles/
A9: GitHub (repositorio y Projects) | B9: GitHub | C9: mes | D9: 0 | E9: =D9*Supuestos!$B$30 -> 0 | F9: 2 | G9: 1 | H9: =E9*F9*G9 -> 0 | I9: Proyecto | J9: Plan Free. https://github.com/pricing
A10: Pasarela MercadoPago (comisión por pedido) | B10: Mercado Pago | C10: pedido | E10: =Supuestos!$B$37 -> 2048.228 | F10: =Supuestos!$B$38 -> 0 | G10: 1 | H10: =E10*F10*G10 -> 0 | I10: Fase 6 | J10: Modo prueba = sin costo. Costo por pedido real = (ticket × 3,29 % + $800) × 1,19 (ver Supuestos).
A11: Internet hogar (prorrateo 30 % del plan) | B11: Operador local | C11: mes | E11: 27000 | F11: 2 | G11: =Cronograma!$F$22 -> 9.1648352 | H11: =E11*F11*G11 -> 494901.1 | I11: Proyecto | J11: Supuesto: plan de $90.000/mes × 30 % de uso para el proyecto, por integrante.
A12: TOTAL | H12: =SUM(H5:H11) -> 651870.57
